{"is_source_file": false, "format": "", "description": "", "external_files": [], "external_methods": [], "published": [], "classes": [], "methods": [], "calls": [], "search-terms": [], "state": 2, "file_id": 12, "knowledge_revision": 24, "git_revision": "a59c7bd30b192003c807d4e6731f5b5485d30f1e", "hash": "39875f2718b0d3819d1e2e2cb4e36c47", "format-version": 4, "code-base-name": "cookie_clicker_frontend", "filename": "README.md", "revision_history": [{"24": "a59c7bd30b192003c807d4e6731f5b5485d30f1e"}]}